experiment_impact_tracker/__init__.py
experiment_impact_tracker/compute_tracker.py
experiment_impact_tracker/create_graph_appendix.py
experiment_impact_tracker/data_info_and_router.py
experiment_impact_tracker/data_utils.py
experiment_impact_tracker/stats.py
experiment_impact_tracker/utils.py
experiment_impact_tracker/version.py
experiment_impact_tracker/cpu/__init__.py
experiment_impact_tracker/cpu/common.py
experiment_impact_tracker/cpu/exceptions.py
experiment_impact_tracker/cpu/intel.py
experiment_impact_tracker/cpu/rapl.py
experiment_impact_tracker/disk/__init__.py
experiment_impact_tracker/disk/common.py
experiment_impact_tracker/emissions/__init__.py
experiment_impact_tracker/emissions/common.py
experiment_impact_tracker/emissions/constants.py
experiment_impact_tracker/emissions/get_region_metrics.py
experiment_impact_tracker/emissions/us_ca_parser.py
experiment_impact_tracker/emissions/data/__init__.py
experiment_impact_tracker/emissions/data/aws_regions.csv
experiment_impact_tracker/emissions/data/azure_regions.json
experiment_impact_tracker/emissions/data/co2eq_parameters.json
experiment_impact_tracker/emissions/data/gcp_regions.csv
experiment_impact_tracker/emissions/data/zone_names.json
experiment_impact_tracker/emissions/data/zonegeometries.json
experiment_impact_tracker/gpu/__init__.py
experiment_impact_tracker/gpu/exceptions.py
experiment_impact_tracker/gpu/nvidia.py
experiment_impact_tracker/gpu/data/tdp.csv
experiment_impact_tracker/operating_system/__init__.py
experiment_impact_tracker/operating_system/common.py
experiment_impact_tracker/py_environment/__init__.py
experiment_impact_tracker/py_environment/common.py
experiment_impact_tracker-0.1.8.data/scripts/create-compute-appendix
experiment_impact_tracker-0.1.8.data/scripts/generate-carbon-impact-statement
experiment_impact_tracker-0.1.8.data/scripts/get-region-emissions-info
experiment_impact_tracker-0.1.8.data/scripts/get-rough-emissions-estimate
experiment_impact_tracker-0.1.8.dist-info/LICENSE
experiment_impact_tracker-0.1.8.dist-info/METADATA
experiment_impact_tracker-0.1.8.dist-info/WHEEL
experiment_impact_tracker-0.1.8.dist-info/top_level.txt
experiment_impact_tracker-0.1.8.dist-info/RECORD
