Metadata-Version: 2.1
Name: experiment-impact-tracker
Version: 0.1.8
Summary: A toolkit for tracking energy, carbon, and compute metrics for machine learning (or any other) experiments.
Home-page: https://github.com/Breakend/experiment-impact-tracker
Author: Peter Henderson
License: MIT
Keywords: machine learning,carbon,energy,compute
Platform: UNKNOWN
Classifier: Development Status :: 3 - Alpha
Classifier: Intended Audience :: Developers
Classifier: Topic :: Software Development :: Build Tools
Classifier: License :: OSI Approved :: MIT License
Classifier: Programming Language :: Python :: 3.5
Classifier: Programming Language :: Python :: 3.6
Classifier: Programming Language :: Python :: 3.7
Requires-Dist: requests
Requires-Dist: bs4
Requires-Dist: shapely
Requires-Dist: scipy
Requires-Dist: joblib
Requires-Dist: numpy
Requires-Dist: pandas (>0.25.0)
Requires-Dist: matplotlib
Requires-Dist: py-cpuinfo
Requires-Dist: pylatex
Requires-Dist: ujson
Requires-Dist: geocoder
Requires-Dist: deepdiff
Requires-Dist: arrow
Requires-Dist: bootstrapped
Requires-Dist: jinja2
Requires-Dist: geopy
Requires-Dist: progiter
Requires-Dist: psutil
Requires-Dist: seaborn
Provides-Extra: docs
Requires-Dist: sphinx ; extra == 'docs'
Requires-Dist: sphinx-autobuild ; extra == 'docs'
Requires-Dist: sphinx-rtd-theme ; extra == 'docs'
Requires-Dist: recommonmark ; extra == 'docs'
Provides-Extra: tests
Requires-Dist: pytest (==3.5.1) ; extra == 'tests'
Requires-Dist: pytest-cov ; extra == 'tests'
Requires-Dist: pytest-env ; extra == 'tests'
Requires-Dist: pytest-xdist ; extra == 'tests'
